Project/biquad_filter.v
module biquad_filter #(
  parameter io_width = 16,
  parameter internal_width = io_width*2
  )(
  input wire clk,
  input wire reset,
  input wire en,

  input wire signed [io_width-1:0] b0,
  input wire signed [io_width-1:0] b1,
  input wire signed [io_width-1:0] b2,
  input wire signed [io_width-1:0] q,
  input wire signed [io_width-1:0] a1,
  input wire signed [io_width-1:0] a2,
  
  input wire signed [io_width-1:0] x,
  output wire signed [io_width-1:0] y
  );
  
  reg signed[io_width-1:0] xin;
  reg signed[io_width-1:0] x_n1, x_n2;
  reg signed[io_width-1:0] y_n1, y_n2;
  wire signed[internal_width-1:0] pb0, pb1, pb2;
  wire signed[internal_width-1:0] pa1, pa2;
 
  wire [5:0] l;
  //wire signed[15:0] pd_check0, pd_check1, pd_check2, pd_check3, pd_check4, pd_check5;
  
  assign pb0 = b0*xin;
  assign pb1 = b1*x_n1;
  assign pb2 = b2*x_n2;
  assign pa1 = a1*y_n1;
  assign pa2 = a2*y_n2;
 
 
  always @(posedge clk, posedge reset) begin
    if (reset)
      xin <= 0;
    else begin
		if (en) xin <= x;
	end
  end
  
  always @(posedge clk, posedge reset) begin
    if (reset)
      x_n1 <= 0;
    else begin
		if (en) x_n1 <= xin;
	end
  end
  
  always @(posedge clk, posedge reset) begin
    if (reset)
      x_n2 <= 0;
    else begin
		if (en) x_n2 <= x_n1;
	end
  end
  
  assign y = (pb0+pb1+pb2-pa1-pa2) >>> q[3:0] ;
  
  always @(posedge clk, posedge reset) begin
    if (reset)
      y_n1 <= 0;
    else begin
		if (en) y_n1 <= y;
	end
  end
  
  always @(posedge clk, posedge reset) begin
    if (reset)
      y_n2 <= 0;
    else begin
		if (en) y_n2 <= y_n1;
	end
  end
  
/*    `ifdef COCOTB_SIM
		initial begin
			$dumpfile ("biquad.vcd");
			$dumpvars(0);
			#1;
		end
  `endif
 */ 
endmodule

Project/DirectForm_I/biquad.vcd
$date
	Thu Jun 24 19:41:32 2021
$end
$version
	Icarus Verilog
$end
$timescale
	1ps
$end
$scope module biquad_filter $end
$var wire 16 ! a1 [15:0] $end
$var wire 16 " a2 [15:0] $end
$var wire 16 # b0 [15:0] $end
$var wire 16 $ b1 [15:0] $end
$var wire 16 % b2 [15:0] $end
$var wire 1 & clk $end
$var wire 1 ' en $end
$var wire 16 ( q [15:0] $end
$var wire 1 ) reset $end
$var wire 16 * x [15:0] $end
$var wire 16 + y [15:0] $end
$var wire 31 , pb2 [30:0] $end
$var wire 31 - pb1 [30:0] $end
$var wire 31 . pb0 [30:0] $end
$var wire 31 / pa2 [30:0] $end
$var wire 31 0 pa1 [30:0] $end
$var reg 16 1 x_n1 [15:0] $end
$var reg 16 2 x_n2 [15:0] $end
$var reg 31 3 xin [30:0] $end
$var reg 16 4 y_n1 [15:0] $end
$var reg 16 5 y_n2 [15:0] $end
$upscope $end
$enddefinitions $end
#0
$dumpvars
b0 5
b0 4
b0 3
b0 2
b0 1
b0 0
b0 /
b0 .
b0 -
b0 ,
b0 +
b1111111111110110 *
1)
b1110 (
1'
1&
b1101000001001110 %
b0 $
b10111110110010 #
b1000001001101 "
b1101010001101111 !
$end
#500000
0)
#5000000
0&
#10000000
b1111111111110111 *
b1111111111111000 +
b1111111111111100010001100001100 .
b1111111111111111111111111110110 3
1&
#15000000
0&
#20000000
b1111111111111000 *
b1111111111110011 +
b1111111111111100101001010111110 .
b1111111111111111111111111110111 3
b1111111111110110 1
b10101110010001000 0
b1111111111111000 4
1&
#25000000
0&
#30000000
b1111111111111001 *
b1111111111111010 +
b1111111111111110111110110011000 /
b1111111111111000 5
b100011011001011101 0
b1111111111110011 4
b11101110011110100 ,
b1111111111110110 2
b1111111111110111 1
b1111111111111101000001001110000 .
b1111111111111111111111111111000 3
1&
#35000000
0&
#40000000
b1111111111111010 *
b0 +
b1111111111111101011001000100010 .
b1111111111111111111111111111001 3
b1111111111111000 1
b11010110101000010 ,
b1111111111110111 2
b10000010101100110 0
b1111111111111010 4
b1111111111111110010110000010111 /
b1111111111110011 5
1&
#45000000
0&
#50000000
b1111111111111011 *
b11 +
b1111111111111111001111000110010 /
b1111111111111010 5
b0 0
b0 4
b10111110110010000 ,
b1111111111111000 2
b1111111111111001 1
b1111111111111101110000111010100 .
b1111111111111111111111111111010 3
1&
#55000000
0&
#60000000
b1111111111111100 *
b1111111111111110001000110000110 .
b1111111111111111111111111111011 3
b1111111111111010 1
b10100110111011110 ,
b1111111111111001 2
b1111111111111110111110101001101 0
b11 4
b0 /
b0 5
1&
#65000000
0&
#70000000
b1111111111111101 *
b10 +
b11000011100111 /
b11 5
b10001111000101100 ,
b1111111111111010 2
b1111111111111011 1
b1111111111111110100000100111000 .
b1111111111111111111111111111100 3
1&
#75000000
0&
#80000000
b1111111111111110 *
b1111111111111110111000011101010 .
b1111111111111111111111111111101 3
b1111111111111100 1
b1110111001111010 ,
b1111111111111011 2
b1111111111111111010100011011110 0
b10 4
1&
#85000000
0&
#90000000
b1111111111111111 *
b10000010011010 /
b10 5
b1011111011001000 ,
b1111111111111100 2
b1111111111111101 1
b1111111111111111010000010011100 .
b1111111111111111111111111111110 3
1&
#95000000
0&
#100000000
b0 *
b1111111111111111101000001001110 .
b1111111111111111111111111111111 3
b1111111111111110 1
b1000111100010110 ,
b1111111111111101 2
1&
#105000000
0&
#110000000
b1 *
b101111101100100 ,
b1111111111111110 2
b1111111111111111 1
b0 .
b0 3
1&
#115000000
0&
#120000000
b10 *
b10111110110010 .
b1 3
b0 1
b10111110110010 ,
b1111111111111111 2
1&
#125000000
0&
#130000000
b11 *
b0 ,
b0 2
b1 1
b101111101100100 .
b10 3
1&
#135000000
0&
#140000000
b100 *
b1000111100010110 .
b11 3
b10 1
b1111111111111111101000001001110 ,
b1 2
1&
#145000000
0&
#150000000
b101 *
b1111111111111111010000010011100 ,
b10 2
b11 1
b1011111011001000 .
b100 3
1&
#155000000
0&
#160000000
b110 *
b1110111001111010 .
b101 3
b100 1
b1111111111111110111000011101010 ,
b11 2
1&
#165000000
0&
#170000000
b111 *
b1111111111111110100000100111000 ,
b100 2
b101 1
b10001111000101100 .
b110 3
1&
#175000000
0&
#180000000
b1000 *
b10100110111011110 .
b111 3
b110 1
b1111111111111110001000110000110 ,
b101 2
1&
#185000000
0&
#190000000
b1001 *
b1111111111111101110000111010100 ,
b110 2
b111 1
b10111110110010000 .
b1000 3
1&
#195000000
0&
#200000000
b11010110101000010 .
b1001 3
b1000 1
b1111111111111101011001000100010 ,
b111 2
1&
#205000000
0&
#210000000
b1 +
b1111111111111101000001001110000 ,
b1000 2
b1001 1
1&
#215000000
0&
#220000000
b0 +
b1111111111111100101001010111110 ,
b1001 2
b1111111111111111101010001101111 0
b1 4
1&
#225000000
0&
#230000000
b1111111111111111 +
b1000001001101 /
b1 5
b0 0
b0 4
1&
