Project/DirectForm_II/biquad_filter.v
module biquad_filter #(
  parameter io_width = 16,
  parameter internal_width = io_width*2-1
  )(
  input wire clk,
  input wire reset,
  input wire en,

  input wire signed [io_width-1:0] b0,
  input wire signed [io_width-1:0] b1,
  input wire signed [io_width-1:0] b2,
  input wire signed [io_width-1:0] q,
  input wire signed [io_width-1:0] a1,
  input wire signed [io_width-1:0] a2,
  
  input wire signed [io_width-1:0] x,
  output wire signed [io_width-1:0] y
  );
  
  localparam signed [io_width-1:0] a0 = 16384;
  reg signed[io_width-1:0] xin;
  wire signed[io_width-1:0] w_n; 
  reg signed[io_width-1:0] w_n1, w_n2;
  wire signed[internal_width-1:0] pd0, pd1, pd2, pd3, pd4, pd5;
  //wire signed[15:0] pd_check0, pd_check1, pd_check2, pd_check3, pd_check4, pd_check5;
  
  assign pd0 = a0*xin;
  assign pd1 = a1*w_n1;
  assign pd2 = a2*w_n2;
  
  always @(posedge clk, posedge reset) begin
    if (reset)
      xin <= 0;
    else begin
		if (en) xin <= x;
	end
  end

  assign w_n = (pd0 - pd1 - pd2) >>> q[3:0];


  always @(posedge clk, posedge reset) begin
    if (reset)
      w_n1 <= 0;
    else begin
		if (en) w_n1 <= w_n;
	end
  end

  always @(posedge clk, posedge reset) begin
    if (reset)
      w_n2 <= 0;
    else begin
		if (en) w_n2 <= w_n1;
	end
  end
    
  assign pd3 = b0*w_n;
  assign pd4 = b1*w_n1;
  assign pd5 = b2*w_n2;
  
  assign y = ((pd3 + pd4 + pd5) >>> (2*q[3:0]-io_width));
   
    `ifdef COCOTB_SIM
		initial begin
			$dumpfile ("biquad.vcd");
			$dumpvars(0);
			#1;
		end
  `endif
  
endmodule

Project/DirectForm_II/biquad.vcd
$date
	Fri Jun 25 00:04:50 2021
$end
$version
	Icarus Verilog
$end
$timescale
	1ps
$end
$scope module biquad_filter $end
$var wire 16 ! a1 [15:0] $end
$var wire 16 " a2 [15:0] $end
$var wire 16 # b0 [15:0] $end
$var wire 16 $ b1 [15:0] $end
$var wire 16 % b2 [15:0] $end
$var wire 1 & clk $end
$var wire 1 ' en $end
$var wire 16 ( q [15:0] $end
$var wire 1 ) reset $end
$var wire 16 * x [15:0] $end
$var wire 16 + y [15:0] $end
$var wire 16 , w_n [15:0] $end
$var wire 31 - pd5 [30:0] $end
$var wire 31 . pd4 [30:0] $end
$var wire 31 / pd3 [30:0] $end
$var wire 31 0 pd2 [30:0] $end
$var wire 31 1 pd1 [30:0] $end
$var wire 31 2 pd0 [30:0] $end
$var reg 16 3 w_n1 [15:0] $end
$var reg 16 4 w_n2 [15:0] $end
$var reg 16 5 xin [15:0] $end
$upscope $end
$enddefinitions $end
#0
$dumpvars
b0 5
b0 4
b0 3
b0 2
b0 1
b0 0
b0 /
b0 .
b0 -
b0 ,
b0 +
b1111111111110110 *
1)
b1110 (
1'
1&
b1110100000100111 %
b0 $
b1011111011001 #
b1000001001101 "
b1101010001101111 !
$end
#500000
0)
#5000000
0&
#10000000
b1111111111110111 *
b1111111111111000 +
b1111111111111110001000110000110 /
b1111111111110110 ,
b1111111111111011000000000000000 2
b1111111111110110 5
1&
#15000000
0&
#20000000
b1111111111111000 *
b1111111111110100 +
b1111111111111101000001001110000 /
b1111111111110000 ,
b1111111111111011100000000000000 2
b1111111111110111 5
b11011001110101010 1
b1111111111110110 3
1&
#25000000
0&
#30000000
b1111111111111001 *
b1111111111111010 +
b1111111111111100110101010010111 /
b1111111111101111 ,
b1111111111111110101110011111110 0
b1110111001111010 -
b1111111111110110 4
b101011100100010000 1
b1111111111110000 3
b1111111111111100000000000000000 2
b1111111111111000 5
1&
#35000000
0&
#40000000
b1111111111111010 *
b1111111111111101001101001001001 /
b1111111111110001 ,
b0 +
b1111111111111100100000000000000 2
b1111111111111001 5
b101110010010100001 1
b1111111111101111 3
b1111111111111101111101100110000 0
b10111110110010000 -
b1111111111110000 4
1&
#45000000
0&
#50000000
b1111111111111011 *
b11 +
b1111111111111101110000111010100 /
b1111111111110100 ,
b1111111111111101110101011100011 0
b11001010101101001 -
b1111111111101111 4
b101000110101111111 1
b1111111111110001 3
b1111111111111101000000000000000 2
b1111111111111010 5
1&
#55000000
0&
#60000000
b1111111111111100 *
b1111111111111110001000110000110 /
b1111111111110110 ,
b11 +
b1111111111111101100000000000000 2
b1111111111111011 5
b100000101011001100 1
b1111111111110100 3
b1111111111111110000101101111101 0
b10110010110110111 -
b1111111111110001 4
1&
#65000000
0&
#70000000
b1111111111111101 *
b10 +
b1111111111111110100000100111000 /
b1111111111111000 ,
b1111111111111110011110001100100 0
b10001111000101100 -
b1111111111110100 4
b11011001110101010 1
b1111111111110110 3
b1111111111111110000000000000000 2
b1111111111111100 5
1&
#75000000
0&
#80000000
b1111111111111110 *
b1111111111111110111000011101010 /
b1111111111111010 ,
b10 +
b1111111111111110100000000000000 2
b1111111111111101 5
b10101110010001000 1
b1111111111111000 3
b1111111111111110101110011111110 0
b1110111001111010 -
b1111111111110110 4
1&
#85000000
0&
#90000000
b1111111111111111 *
b1111111111111111000100011000011 /
b1111111111111011 ,
b1111111111111110111110110011000 0
b1011111011001000 -
b1111111111111000 4
b10000010101100110 1
b1111111111111010 3
b1111111111111111000000000000000 2
b1111111111111110 5
1&
#95000000
0&
#100000000
b0 *
b1111111111111111011100001110101 /
b1111111111111101 ,
b10 +
b1111111111111111100000000000000 2
b1111111111111111 5
b1101100111010101 1
b1111111111111011 3
b1111111111111111001111000110010 0
b1000111100010110 -
b1111111111111010 4
1&
#105000000
0&
#110000000
b1 *
b1111111111111111110100000100111 /
b1111111111111111 ,
b1111111111111111010111001111111 0
b111011100111101 -
b1111111111111011 4
b1000001010110011 1
b1111111111111101 3
b0 2
b0 5
1&
#115000000
0&
#120000000
b10 *
b1011111011001 /
b1 ,
b10 +
b100000000000000 2
b1 5
b10101110010001 1
b1111111111111111 3
b1111111111111111100111100011001 0
b100011110001011 -
b1111111111111101 4
1&
#125000000
0&
#130000000
b11 *
b10111110110010 /
b10 ,
b1111111111111111110111110110011 0
b1011111011001 -
b1111111111111111 4
b1111111111111111101010001101111 1
b1 3
b1000000000000000 2
b10 5
1&
#135000000
0&
#140000000
b100 *
b101111101100100 /
b100 ,
b10 +
b1100000000000000 2
b11 5
b1111111111111111010100011011110 1
b10 3
b1000001001101 0
b1111111111111111110100000100111 -
b1 4
1&
#145000000
0&
#150000000
b101 *
b1000111100010110 /
b110 ,
b10000010011010 0
b1111111111111111101000001001110 -
b10 4
b1111111111111110101000110111100 1
b100 3
b10000000000000000 2
b100 5
1&
#155000000
0&
#160000000
b110 *
b1011111011001000 /
b1000 ,
b10 +
b10100000000000000 2
b101 5
b1111111111111101111101010011010 1
b110 3
b100000100110100 0
b1111111111111111010000010011100 -
b100 4
1&
#165000000
0&
#170000000
b111 *
b1101011010100001 /
b1001 ,
b110000111001110 0
b1111111111111110111000011101010 -
b110 4
b1111111111111101010001101111000 1
b1000 3
b11000000000000000 2
b110 5
1&
#175000000
0&
#180000000
b1000 *
b10000011001010011 /
b1011 ,
b10 +
b11100000000000000 2
b111 5
b1111111111111100111011111100111 1
b1001 3
b1000001001101000 0
b1111111111111110100000100111000 -
b1000 4
1&
#185000000
0&
#190000000
b1001 *
b10011011000000101 /
b1101 ,
b1001001010110101 0
b1111111111111110010100101011111 -
b1001 4
b1111111111111100010000011000101 1
b1011 3
b100000000000000000 2
b1000 5
1&
#195000000
0&
#200000000
b10110010110110111 /
b1111 ,
b10 +
b100100000000000000 2
b1001 5
b1111111111111011100100110100011 1
b1101 3
b1011001101001111 0
b1111111111111101111100110101101 -
b1011 4
1&
#205000000
0&
#210000000
b1 +
b1101001111101001 0
b1111111111111101100100111111011 -
b1101 4
b1111111111111010111001010000001 1
b1111 3
1&
#215000000
0&
#220000000
b0 +
b1111010010000011 0
b1111111111111101001101001001001 -
b1111 4
1&
